LICENSE
README.md
intruder.py
setup.py
intruder.egg-info/PKG-INFO
intruder.egg-info/SOURCES.txt
intruder.egg-info/dependency_links.txt
intruder.egg-info/entry_points.txt
intruder.egg-info/requires.txt
intruder.egg-info/top_level.txt