Metadata-Version: 2.1
Name: intruder
Version: 0.1.4
Summary: HTTP/HTTPS request fuzzer
Home-page: https://github.com/lpiekarski/intruder
Author: Łukasz Piekarski
Author-email: lukasz.piekarski.001@gmail.com
License: UNKNOWN
Platform: UNKNOWN
License-File: LICENSE
